slumpy/__init__.py
slumpy/boolum_type.py
slumpy/intum_type.py
slumpy/realum_type.py
slumpy/strum_type.py
slumpy-0.1.6.dist-info/LICENSE
slumpy-0.1.6.dist-info/METADATA
slumpy-0.1.6.dist-info/WHEEL
slumpy-0.1.6.dist-info/top_level.txt
slumpy-0.1.6.dist-info/RECORD
